smersh_cli/__init__.py
smersh_cli/__main__.py
smersh_cli/api.py
smersh_cli/models.py
smersh_cli/locale/fr/LC_MESSAGES/smersh-cli.mo
smersh_cli/locale/fr/LC_MESSAGES/smersh-cli.po
smersh_cli/utils/__init__.py
smersh_cli/utils/case.py
smersh_cli/utils/date.py
smersh_cli/utils/json.py
smersh_cli-1.0.2.dist-info/LICENSE
smersh_cli-1.0.2.dist-info/METADATA
smersh_cli-1.0.2.dist-info/WHEEL
smersh_cli-1.0.2.dist-info/entry_points.txt
smersh_cli-1.0.2.dist-info/top_level.txt
smersh_cli-1.0.2.dist-info/RECORD
