Metadata-Version: 2.1
Name: smersh-cli
Version: 1.0.2
Summary: A SMERSH command-line client
Home-page: https://smersh.app/
Author: CMEPW
Author-email: cmepw@protonmail.com
License: UNKNOWN
Project-URL: Source, https://github.com/CMEPW/smersh-cli
Platform: UNKNOWN
Classifier: Intended Audience :: End Users/Desktop
Classifier: Topic :: Security
Classifier: Natural Language :: English
Classifier: Operating System :: POSIX
Classifier: Operating System :: POSIX :: BSD
Classifier: Operating System :: POSIX :: Linux
Classifier: Operating System :: MacOS :: MacOS X
Classifier: Operating System :: Microsoft :: Windows
Classifier: Programming Language :: Python
Classifier: Programming Language :: Python :: 3
Classifier: Programming Language :: Python :: 3 :: Only
Classifier: Programming Language :: Python :: 3.5
Classifier: Programming Language :: Python :: 3.6
Classifier: Programming Language :: Python :: 3.7
Classifier: Programming Language :: Python :: 3.8
Classifier: Programming Language :: Python :: 3.9
Requires-Python: >=3.5
License-File: LICENSE
Requires-Dist: rich
Requires-Dist: dataclasses-json
Requires-Dist: requests
Requires-Dist: pydantic
Requires-Dist: cmd2
Requires-Dist: importlib-metadata (>=3.6)
